aamad/__init__.py
aamad/cli.py
aamad/installer.py
aamad/data/aamad_bundle.zip
aamad-0.1.0.dist-info/LICENSE
aamad-0.1.0.dist-info/METADATA
aamad-0.1.0.dist-info/WHEEL
aamad-0.1.0.dist-info/entry_points.txt
aamad-0.1.0.dist-info/top_level.txt
aamad-0.1.0.dist-info/RECORD
