Metadata-Version: 2.1
Name: aamad
Version: 0.1.0
Summary: AI-Assisted Multi-Agent Development framework artifacts and installer
Author: Synaptic AI Consulting
License: Apache-2.0
Project-URL: Homepage, https://github.com/synaptic-ai-consulting/AAMAD
Project-URL: Documentation, https://github.com/synaptic-ai-consulting/AAMAD#readme
Project-URL: Repository, https://github.com/synaptic-ai-consulting/AAMAD.git
Keywords: multi-agent,crew,automation,prompt-engineering
Classifier: License :: OSI Approved :: Apache Software License
Classifier: Programming Language :: Python :: 3
Classifier: Programming Language :: Python :: 3 :: Only
Classifier: Programming Language :: Python :: 3.9
Classifier: Programming Language :: Python :: 3.10
Classifier: Programming Language :: Python :: 3.11
Classifier: Programming Language :: Python :: 3.12
Classifier: Topic :: Software Development :: Build Tools
Classifier: Topic :: Software Development :: Libraries
Requires-Python: >=3.9
License-File: LICENSE
